Instr/rom.sv
module rom #(
    parameter   ADDRESS_WIDTH = 8,
                DATA_WIDTH = 32
)(
    input   logic               clk,
    input   logic [ADDRESS_WIDTH-1:0] addr,
    output  logic [DATA_WIDTH-1:0] dout
);

    logic   [DATA_WIDTH-1:0] rom_array [2**ADDRESS_WIDTH-1:0];

    initial begin
            $display("Loading rom.");
            $readmemh("program.mem", rom_array);
    end;

    always @(posedge clk)
        dout = rom_array[addr];

endmodule

Instr/rom.vcd
$version Generated by VerilatedVcd $end
$date Thu Nov 17 12:42:28 2022 $end
$timescale 1ps $end

 $scope module TOP $end
  $var wire  8 $ addr [7:0] $end
  $var wire  1 # clk $end
  $var wire 32 % dout [31:0] $end
  $scope module rom $end
   $var wire 32 & ADDRESS_WIDTH [31:0] $end
   $var wire 32 ' DATA_WIDTH [31:0] $end
   $var wire  8 $ addr [7:0] $end
   $var wire  1 # clk $end
   $var wire 32 % dout [31:0] $end
  $upscope $end
 $upscope $end
$enddefinitions $end


#0
1#
b00000000 $
b00000000000000000000000000000000 %
b00000000000000000000000000001000 &
b00000000000000000000000000100000 '
#1
0#
#2
1#
b00001111111100000000001100010011 %
#3
0#
#4
1#
b00000001 $
#5
0#
#6
1#
b00000010 $
b00000000000000000000000000000000 %
#7
0#
#8
1#
b00000011 $
#9
0#
#10
1#
b00000100 $
#11
0#
#12
1#
b00000101 $
b00000000000000000000010100010011 %
#13
0#
#14
1#
b00000110 $
b00000000000000000000000000000000 %
#15
0#
#16
1#
b00000111 $
#17
0#
#18
1#
b00001000 $
#19
0#
#20
1#
b00001001 $
b00000000000000000000010110010011 %
#21
0#
#22
1#
b00001010 $
b00000000000000000000000000000000 %
#23
0#
#24
1#
b00001011 $
b00000000000101011000010110010011 %
#25
0#
#26
1#
b00001100 $
b00000000000000000000000000000000 %
#27
0#
#28
1#
b00001101 $
b00000000000001011000010100010011 %
#29
0#
#30
1#
b00001110 $
b00000000000000000000000000000000 %
#31
0#
#32
1#
b00001111 $
b11111110011001011001110011100011 %
#33
0#
#34
1#
b00010000 $
b00000000000000000000000000000000 %
#35
0#
#36
1#
b00010001 $
#37
0#
#38
1#
b00010010 $
#39
0#
#40
1#
b00010011 $
#41
0#
#42
1#
b00010100 $
#43
0#
#44
1#
b00010101 $
#45
0#
#46
1#
b00010110 $
#47
0#
#48
1#
b00010111 $
#49
0#
#50
1#
b00011000 $
#51
0#
#52
1#
b00011001 $
#53
0#
#54
1#
b00011010 $
#55
0#
#56
1#
b00011011 $
#57
0#
#58
1#
b00011100 $
#59
0#
#60
1#
b00011101 $
#61
0#
#62
1#
b00011110 $
#63
0#
#64
1#
b00011111 $
#65
0#
#66
1#
b00100000 $
#67
0#
#68
1#
b00100001 $
#69
0#
#70
1#
b00100010 $
#71
0#
#72
1#
b00100011 $
#73
0#
#74
1#
b00100100 $
#75
0#
#76
1#
b00100101 $
#77
0#
#78
1#
b00100110 $
#79
0#
#80
1#
b00100111 $
#81
0#
#82
1#
b00101000 $
#83
0#
#84
1#
b00101001 $
#85
0#
#86
1#
b00101010 $
#87
0#
#88
1#
b00101011 $
#89
0#
#90
1#
b00101100 $
#91
0#
#92
1#
b00101101 $
#93
0#
#94
1#
b00101110 $
#95
0#
#96
1#
b00101111 $
#97
0#
#98
1#
b00110000 $
