alu_regfile/alu.sv


//  | 31-25 | 24-20 | 19-15 | 14-12 | 11-7 |  6-0  |
//  | func7 |  rd2  |  rd1  | func3 | rd   | opcode|

module alu #(

    DATA_WIDTH = 32, 
    CONTROL_WIDTH = 3

) (
    input logic [CONTROL_WIDTH-1:0]         ALUctrl,
    input logic [DATA_WIDTH-1:0]            ALUop1,
    input logic [DATA_WIDTH-1:0]            ALUop2,
    output logic [DATA_WIDTH-1:0]           ALUout,
    output logic                            EQ

);


always_comb begin
    //As encouraged by prof, implementing all alu functions although add only needed
    case (ALUctrl) //LECTURE 7 slide 19
    3'h0:   ALUout = ALUop1 + ALUop2;
    3'h1:   ALUout = ALUop1 - ALUop2;
    3'h2:   ALUout = ALUop1 & ALUop2;
    3'h3:   ALUout = ALUop1 | ALUop2;
    3'h5:   ALUout = ALUop1 < ALUop2 ? 1 : 0;
    default: ALUout = 0;
    endcase
    assign EQ = (ALUop1 == ALUop2);


end
endmodule

src/alu_regfile/regfile.sv
module regfile #(
    ADDRESS_WIDTH = 5, 
    DATA_WIDTH = 32 

) (
    input logic                             clk,
    input logic [ADDRESS_WIDTH-1:0]         AD1,
    input logic [ADDRESS_WIDTH-1:0]         AD2,
    input logic [ADDRESS_WIDTH-1:0]         AD3,
    input logic                             WE3,
    input logic [DATA_WIDTH-1:0]            WD3,
    output logic [DATA_WIDTH-1:0]           RD1,
    output logic [DATA_WIDTH-1:0]           RD2,
    output logic [DATA_WIDTH-1:0]           a0

);

logic [DATA_WIDTH-1:0] ram_array [2**ADDRESS_WIDTH-1:0];

always_comb begin
    assign RD1 = ram_array[AD1];
    assign RD2 = ram_array[AD2];
    assign a0 = ram_array[10];
end

always_ff @(posedge clk) begin
    if(WE3 == 1'b1)
        ram_array[AD3] <= WD3;
end

endmodule

src/alu_regfile/reg_alu_top.sv
/* verilator lint_off UNUSED*/
// above line to stop verilator from nagging me for not using all the bits of instr

module reg_alu_top #(
    IMMOP_WIDTH = 32,
    INSTR_WIDTH = 32,
    ADDRESS_WIDTH = 5, 
    DATA_WIDTH = 32, 
    CONTROL_WIDTH = 3

) (
    input logic                           clk,
    input logic                           ALUsrc,
    input logic [CONTROL_WIDTH-1:0]       ALUctrl,
    input logic                           RegWrite,
    input logic  [INSTR_WIDTH-1:0]        instr, //combine rs1, rs2. rd into one for brevity
    input logic  [IMMOP_WIDTH-1:0]        ImmOp,
    output logic [DATA_WIDTH-1:0]         a0,
    output logic                          EQ
);


//  | 31-25 | 24-20 | 19-15 | 14-12 | 11-7 |  6-0 |
//  | func7 |  rs2  |  rs1  | func3 |  rd  |opcode| 
//  |    imm 11:0   |  rs1  | func3 |  rd  |opcode| 


logic [ADDRESS_WIDTH-1:0] rs2 = instr[24:20];
logic [ADDRESS_WIDTH-1:0] rs1 = instr[19:15];
logic [ADDRESS_WIDTH-1:0] rd = instr[11:7];
logic [DATA_WIDTH-1:0] ALUop1;
logic [DATA_WIDTH-1:0] ALUop2;
logic [DATA_WIDTH-1:0] regOp2;
logic [DATA_WIDTH-1:0] ALUout;

assign ALUop2 = ALUsrc ? ImmOp : regOp2; //shortcut method, no need for a mux module

regfile regfile (
    .clk (clk),
    .AD1 (rs1),
    .AD2 (rs2),
    .AD3 (rd),
    .WE3 (RegWrite),
    .WD3 (ALUout),
    .RD1 (ALUop1),
    .RD2 (regOp2),
    .a0 (a0)
);


alu alu (
    .ALUop1 (ALUop1),
    .ALUop2 (ALUop2), 
    .ALUctrl (ALUctrl),
    .ALUout (ALUout),
    .EQ (EQ)
);

endmodule

src/alu_regfile/reg_alu_top.vcd
$version Generated by VerilatedVcd $end
$date Fri Nov 25 13:09:09 2022 $end
$timescale 1ps $end

 $scope module TOP $end
  $var wire  3 E ALUctrl [2:0] $end
  $var wire  1 D ALUsrc $end
  $var wire  1 J EQ $end
  $var wire 32 H ImmOp [31:0] $end
  $var wire  1 F RegWrite $end
  $var wire 32 I a0 [31:0] $end
  $var wire  1 C clk $end
  $var wire 32 G instr [31:0] $end
  $scope module reg_alu_top $end
   $var wire 32 S ADDRESS_WIDTH [31:0] $end
   $var wire  3 E ALUctrl [2:0] $end
   $var wire 32 N ALUop1 [31:0] $end
   $var wire 32 O ALUop2 [31:0] $end
   $var wire 32 Q ALUout [31:0] $end
   $var wire  1 D ALUsrc $end
   $var wire 32 T CONTROL_WIDTH [31:0] $end
   $var wire 32 R DATA_WIDTH [31:0] $end
   $var wire  1 J EQ $end
   $var wire 32 R IMMOP_WIDTH [31:0] $end
   $var wire 32 R INSTR_WIDTH [31:0] $end
   $var wire 32 H ImmOp [31:0] $end
   $var wire  1 F RegWrite $end
   $var wire 32 I a0 [31:0] $end
   $var wire  1 C clk $end
   $var wire 32 G instr [31:0] $end
   $var wire  5 M rd [4:0] $end
   $var wire 32 P regOp2 [31:0] $end
   $var wire  5 L rs1 [4:0] $end
   $var wire  5 K rs2 [4:0] $end
   $scope module alu $end
    $var wire  3 E ALUctrl [2:0] $end
    $var wire 32 N ALUop1 [31:0] $end
    $var wire 32 O ALUop2 [31:0] $end
    $var wire 32 Q ALUout [31:0] $end
    $var wire 32 T CONTROL_WIDTH [31:0] $end
    $var wire 32 R DATA_WIDTH [31:0] $end
    $var wire  1 J EQ $end
   $upscope $end
   $scope module regfile $end
    $var wire  5 L AD1 [4:0] $end
    $var wire  5 K AD2 [4:0] $end
    $var wire  5 M AD3 [4:0] $end
    $var wire 32 S ADDRESS_WIDTH [31:0] $end
    $var wire 32 R DATA_WIDTH [31:0] $end
    $var wire 32 N RD1 [31:0] $end
    $var wire 32 P RD2 [31:0] $end
    $var wire 32 Q WD3 [31:0] $end
    $var wire  1 F WE3 $end
    $var wire 32 I a0 [31:0] $end
    $var wire  1 C clk $end
    $var wire 32 # ram_array[0] [31:0] $end
    $var wire 32 - ram_array[10] [31:0] $end
    $var wire 32 . ram_array[11] [31:0] $end
    $var wire 32 / ram_array[12] [31:0] $end
    $var wire 32 0 ram_array[13] [31:0] $end
    $var wire 32 1 ram_array[14] [31:0] $end
    $var wire 32 2 ram_array[15] [31:0] $end
    $var wire 32 3 ram_array[16] [31:0] $end
    $var wire 32 4 ram_array[17] [31:0] $end
    $var wire 32 5 ram_array[18] [31:0] $end
    $var wire 32 6 ram_array[19] [31:0] $end
    $var wire 32 $ ram_array[1] [31:0] $end
    $var wire 32 7 ram_array[20] [31:0] $end
    $var wire 32 8 ram_array[21] [31:0] $end
    $var wire 32 9 ram_array[22] [31:0] $end
    $var wire 32 : ram_array[23] [31:0] $end
    $var wire 32 ; ram_array[24] [31:0] $end
    $var wire 32 < ram_array[25] [31:0] $end
    $var wire 32 = ram_array[26] [31:0] $end
    $var wire 32 > ram_array[27] [31:0] $end
    $var wire 32 ? ram_array[28] [31:0] $end
    $var wire 32 @ ram_array[29] [31:0] $end
    $var wire 32 % ram_array[2] [31:0] $end
    $var wire 32 A ram_array[30] [31:0] $end
    $var wire 32 B ram_array[31] [31:0] $end
    $var wire 32 & ram_array[3] [31:0] $end
    $var wire 32 ' ram_array[4] [31:0] $end
    $var wire 32 ( ram_array[5] [31:0] $end
    $var wire 32 ) ram_array[6] [31:0] $end
    $var wire 32 * ram_array[7] [31:0] $end
    $var wire 32 + ram_array[8] [31:0] $end
    $var wire 32 , ram_array[9] [31:0] $end
   $upscope $end
  $upscope $end
 $upscope $end
$enddefinitions $end


#0
b00000000000000000000000000000000 #
b00000000000000000000000000000000 $
b00000000000000000000000000000000 %
b00000000000000000000000000000000 &
b00000000000000000000000000000000 '
b00000000000000000000000000000000 (
b00000000000000000000000000000000 )
b00000000000000000000000000000000 *
b00000000000000000000000000000000 +
b00000000000000000000000000000000 ,
b00000000000000000000000000000000 -
b00000000000000000000000000000000 .
b00000000000000000000000000000000 /
b00000000000000000000000000000000 0
b00000000000000000000000000000000 1
b00000000000000000000000000000000 2
b00000000000000000000000000000000 3
b00000000000000000000000000000000 4
b00000000000000000000000000000000 5
b00000000000000000000000000000000 6
b00000000000000000000000000000000 7
b00000000000000000000000000000000 8
b00000000000000000000000000000000 9
b00000000000000000000000000000000 :
b00000000000000000000000000000000 ;
b00000000000000000000000000000000 <
b00000000000000000000000000000000 =
b00000000000000000000000000000000 >
b00000000000000000000000000000000 ?
b00000000000000000000000000000000 @
b00000000000000000000000000000000 A
b00000000000000000000000000000000 B
1C
0D
b000 E
0F
b00000000000000000000000000000000 G
b00000000000000000000000000000000 H
b00000000000000000000000000000000 I
0J
b00000 K
b00000 L
b00000 M
b00000000000000000000000000000000 N
b00000000000000000000000000000000 O
b00000000000000000000000000000000 P
b00000000000000000000000000000000 Q
b00000000000000000000000000100000 R
b00000000000000000000000000000101 S
b00000000000000000000000000000011 T
#1
0C
1J
#2
1C
1D
1F
b00001111001100000000100100010011 G
b00000000000000000000000011110011 H
b10011 K
b10010 M
#3
0C
0J
b00000000000000000000000011110011 O
b00000000000000000000000011110011 Q
#4
b00000000000000000000000011110011 5
1C
0D
b00000000000010010000010110010011 G
b00000000000000000000000000000000 H
b00000 K
b10010 L
b01011 M
#5
0C
b00000000000000000000000011110011 N
b00000000000000000000000000000000 O
#6
b00000000000000000000000011110011 .
1C
1D
b00000000000101010000010100010011 G
b00000000000000000000000000000001 H
b00001 K
b01010 L
b01010 M
#7
0C
b00000000000000000000000000000000 N
b00000000000000000000000000000001 O
b00000000000000000000000000000001 Q
#8
b00000000000000000000000000000001 -
1C
b00000000000000000000000000000001 I
1J
b00000000000000000000000000000001 N
b00000000000000000000000000000010 Q
#9
0C
#10
b00000000000000000000000000000010 -
1C
b00000000000000000000000000000010 I
0J
b00000000000000000000000000000010 N
b00000000000000000000000000000011 Q
#11
0C
#12
b00000000000000000000000000000011 -
1C
b00000000000000000000000000000011 I
b00000000000000000000000000000011 N
b00000000000000000000000000000100 Q
#13
0C
#14
b00000000000000000000000000000100 -
1C
b00000000000000000000000000000100 I
b00000000000000000000000000000100 N
b00000000000000000000000000000101 Q
#15
0C
#16
b00000000000000000000000000000101 -
1C
b00000000000000000000000000000101 I
b00000000000000000000000000000101 N
b00000000000000000000000000000110 Q
#17
0C
#18
b00000000000000000000000000000110 -
1C
b00000000000000000000000000000110 I
b00000000000000000000000000000110 N
b00000000000000000000000000000111 Q
#19
0C
#20
b00000000000000000000000000000111 -
1C
b00000000000000000000000000000111 I
b00000000000000000000000000000111 N
b00000000000000000000000000001000 Q
#21
0C
#22
b00000000000000000000000000001000 -
1C
b00000000000000000000000000001000 I
b00000000000000000000000000001000 N
b00000000000000000000000000001001 Q
#23
0C
#24
b00000000000000000000000000001001 -
1C
b00000000000000000000000000001001 I
b00000000000000000000000000001001 N
b00000000000000000000000000001010 Q
#25
0C
#26
b00000000000000000000000000001010 -
1C
b00000000000000000000000000001010 I
b00000000000000000000000000001010 N
b00000000000000000000000000001011 Q
#27
0C
#28
b00000000000000000000000000001011 -
1C
b00000000000000000000000000001011 I
b00000000000000000000000000001011 N
b00000000000000000000000000001100 Q
#29
0C
#30
b00000000000000000000000000001100 -
1C
b00000000000000000000000000001100 I
b00000000000000000000000000001100 N
b00000000000000000000000000001101 Q
#31
0C
#32
b00000000000000000000000000001101 -
1C
b00000000000000000000000000001101 I
b00000000000000000000000000001101 N
b00000000000000000000000000001110 Q
#33
0C
#34
b00000000000000000000000000001110 -
1C
b00000000000000000000000000001110 I
b00000000000000000000000000001110 N
b00000000000000000000000000001111 Q
#35
0C
#36
b00000000000000000000000000001111 -
1C
b00000000000000000000000000001111 I
b00000000000000000000000000001111 N
b00000000000000000000000000010000 Q
#37
0C
#38
b00000000000000000000000000010000 -
1C
b00000000000000000000000000010000 I
b00000000000000000000000000010000 N
b00000000000000000000000000010001 Q
#39
0C
#40
b00000000000000000000000000010001 -
1C
b00000000000000000000000000010001 I
b00000000000000000000000000010001 N
b00000000000000000000000000010010 Q
#41
0C
#42
b00000000000000000000000000010010 -
1C
b00000000000000000000000000010010 I
b00000000000000000000000000010010 N
b00000000000000000000000000010011 Q
#43
0C
#44
b00000000000000000000000000010011 -
1C
b00000000000000000000000000010011 I
b00000000000000000000000000010011 N
b00000000000000000000000000010100 Q
#45
0C
#46
b00000000000000000000000000010100 -
1C
b00000000000000000000000000010100 I
b00000000000000000000000000010100 N
b00000000000000000000000000010101 Q
#47
0C
#48
b00000000000000000000000000010101 -
1C
b00000000000000000000000000010101 I
b00000000000000000000000000010101 N
b00000000000000000000000000010110 Q
