src/PC/register.sv
module register#(
    parameter WIDTH = 32
)(
    input   logic   clk,
    input   logic   rst,
    input   logic [WIDTH-1:0]   next_PC,
    output  logic [WIDTH-1:0]   PC
);

reg [WIDTH-1:0] current_PC;

always_ff @ (posedge clk)
    if (rst) current_PC <= {WIDTH{1'b0}};
    else current_PC <= next_PC;

assign PC = current_PC;
endmodule

src/PC/PC.sv
module PC #(
    parameter WIDTH = 32
) (
    input   logic [WIDTH-1:0]   ImmOp,
    input   logic               clk,
    input   logic               rst,
    input   logic               jmp_sel,
    output  logic [WIDTH-1:0]   PC_OUT
);

logic [WIDTH-1:0] branch_PC;
logic [WIDTH-1:0] current_PC;

register PCReg (
    .PC(current_PC),
    .next_PC(branch_PC),
    .clk(clk),
    .rst(rst)
);

always_comb begin
    branch_PC = (jmp_sel) ? current_PC+ImmOp:current_PC+4;
end

assign PC_OUT = current_PC;
endmodule

PC/PC.vcd
$version Generated by VerilatedVcd $end
$date Thu Nov 17 10:50:45 2022 $end
$timescale 1ps $end

 $scope module TOP $end
  $var wire  8 # ImmOp [7:0] $end
  $var wire  8 ' PC_OUT [7:0] $end
  $var wire  1 $ clk $end
  $var wire  1 & jmp_sel $end
  $var wire  1 % rst $end
  $scope module PC $end
   $var wire  8 # ImmOp [7:0] $end
   $var wire  8 ' PC_OUT [7:0] $end
   $var wire 32 * WIDTH [31:0] $end
   $var wire  8 ( branch_PC [7:0] $end
   $var wire  1 $ clk $end
   $var wire  8 ) current_PC [7:0] $end
   $var wire  1 & jmp_sel $end
   $var wire  1 % rst $end
   $scope module PCReg $end
    $var wire  8 ) PC [7:0] $end
    $var wire 32 * WIDTH [31:0] $end
    $var wire  1 $ clk $end
    $var wire  8 ) current_PC [7:0] $end
    $var wire  8 ( next_PC [7:0] $end
    $var wire  1 % rst $end
   $upscope $end
  $upscope $end
 $upscope $end
$enddefinitions $end


#0
b00000000 #
1$
0%
0&
b00000000 '
b00000100 (
b00000000 )
b00000000000000000000000000001000 *
#1
0$
#2
1$
b00000100 '
b00001000 (
b00000100 )
#3
0$
#4
1$
b00001000 '
b00001100 (
b00001000 )
#5
0$
#6
1$
b00001100 '
b00010000 (
b00001100 )
#7
0$
#8
1$
b00010000 '
b00010100 (
b00010000 )
#9
0$
#10
1$
b00010100 '
b00011000 (
b00010100 )
#11
0$
#12
1$
b00011000 '
b00011100 (
b00011000 )
#13
0$
#14
1$
b00011100 '
b00100000 (
b00011100 )
#15
0$
#16
1$
b00100000 '
b00100100 (
b00100000 )
#17
0$
#18
1$
b00100100 '
b00101000 (
b00100100 )
#19
0$
#20
1$
b00101000 '
b00101100 (
b00101000 )
#21
0$
#22
1$
b00101100 '
b00110000 (
b00101100 )
#23
0$
#24
1$
b00110000 '
b00110100 (
b00110000 )
#25
0$
#26
1$
b00110100 '
b00111000 (
b00110100 )
#27
0$
#28
1$
b00111000 '
b00111100 (
b00111000 )
#29
0$
#30
1$
b00111100 '
b01000000 (
b00111100 )
#31
0$
#32
1$
b01000000 '
b01000100 (
b01000000 )
#33
0$
#34
1$
b01000100 '
b01001000 (
b01000100 )
#35
0$
#36
1$
b01001000 '
b01001100 (
b01001000 )
#37
0$
#38
1$
b01001100 '
b01010000 (
b01001100 )
#39
0$
#40
1$
b01010000 '
b01010100 (
b01010000 )
#41
0$
#42
1$
b01010100 '
b01011000 (
b01010100 )
#43
0$
#44
1$
b01011000 '
b01011100 (
b01011000 )
#45
0$
#46
1$
b01011100 '
b01100000 (
b01011100 )
#47
0$
#48
1$
b01100000 '
b01100100 (
b01100000 )
#49
0$
#50
1$
b01100100 '
b01101000 (
b01100100 )
#51
0$
#52
1$
b01101000 '
b01101100 (
b01101000 )
#53
0$
#54
1$
b01101100 '
b01110000 (
b01101100 )
#55
0$
#56
1$
b01110000 '
b01110100 (
b01110000 )
#57
0$
#58
1$
b01110100 '
b01111000 (
b01110100 )
#59
0$
#60
1$
b01111000 '
b01111100 (
b01111000 )
#61
0$
#62
1$
b01111100 '
b10000000 (
b01111100 )
#63
0$
#64
1$
b10000000 '
b10000100 (
b10000000 )
#65
0$
#66
1$
b10000100 '
b10001000 (
b10000100 )
#67
0$
#68
1$
b10001000 '
b10001100 (
b10001000 )
#69
0$
#70
1$
b10001100 '
b10010000 (
b10001100 )
#71
0$
#72
1$
b10010000 '
b10010100 (
b10010000 )
#73
0$
#74
1$
b10010100 '
b10011000 (
b10010100 )
#75
0$
#76
1$
b10011000 '
b10011100 (
b10011000 )
#77
0$
#78
1$
b10011100 '
b10100000 (
b10011100 )
#79
0$
#80
1$
b10100000 '
b10100100 (
b10100000 )
#81
0$
#82
1$
b10100100 '
b10101000 (
b10100100 )
#83
0$
#84
1$
b10101000 '
b10101100 (
b10101000 )
#85
0$
#86
1$
b10101100 '
b10110000 (
b10101100 )
#87
0$
#88
1$
b10110000 '
b10110100 (
b10110000 )
#89
0$
#90
1$
b10110100 '
b10111000 (
b10110100 )
#91
0$
#92
1$
b10111000 '
b10111100 (
b10111000 )
#93
0$
#94
1$
b10111100 '
b11000000 (
b10111100 )
#95
0$
#96
1$
b11000000 '
b11000100 (
b11000000 )
#97
0$
#98
1$
b11000100 '
b11001000 (
b11000100 )
#99
0$
#100
1$
b11001000 '
b11001100 (
b11001000 )
#101
0$
#102
1$
b11001100 '
b11010000 (
b11001100 )
#103
0$
#104
1$
b11010000 '
b11010100 (
b11010000 )
#105
0$
#106
1$
b11010100 '
b11011000 (
b11010100 )
#107
0$
#108
1$
b11011000 '
b11011100 (
b11011000 )
#109
0$
#110
1$
b11011100 '
b11100000 (
b11011100 )
#111
0$
#112
1$
b11100000 '
b11100100 (
b11100000 )
#113
0$
#114
1$
b11100100 '
b11101000 (
b11100100 )
#115
0$
#116
1$
b11101000 '
b11101100 (
b11101000 )
#117
0$
#118
1$
b11101100 '
b11110000 (
b11101100 )
#119
0$
#120
1$
b11110000 '
b11110100 (
b11110000 )
#121
0$
#122
1$
b11110100 '
b11111000 (
b11110100 )
#123
0$
#124
1$
b11111000 '
b11111100 (
b11111000 )
#125
0$
#126
1$
b11111100 '
b00000000 (
b11111100 )
#127
0$
#128
1$
b00000000 '
b00000100 (
b00000000 )
#129
0$
#130
1$
b00000100 '
b00001000 (
b00000100 )
#131
0$
#132
1$
b00001000 '
b00001100 (
b00001000 )
#133
0$
#134
1$
b00001100 '
b00010000 (
b00001100 )
#135
0$
#136
1$
b00010000 '
b00010100 (
b00010000 )
#137
0$
#138
1$
b00010100 '
b00011000 (
b00010100 )
#139
0$
#140
1$
b00011000 '
b00011100 (
b00011000 )
#141
0$
#142
1$
b00011100 '
b00100000 (
b00011100 )
#143
0$
#144
1$
b00100000 '
b00100100 (
b00100000 )
#145
0$
#146
1$
b00100100 '
b00101000 (
b00100100 )
#147
0$
#148
1$
b00101000 '
b00101100 (
b00101000 )
#149
0$
#150
1$
b00101100 '
b00110000 (
b00101100 )
#151
0$
#152
1$
b00110000 '
b00110100 (
b00110000 )
#153
0$
#154
1$
b00110100 '
b00111000 (
b00110100 )
#155
0$
#156
1$
b00111000 '
b00111100 (
b00111000 )
#157
0$
#158
1$
b00111100 '
b01000000 (
b00111100 )
#159
0$
#160
1$
b01000000 '
b01000100 (
b01000000 )
#161
0$
#162
1$
b01000100 '
b01001000 (
b01000100 )
#163
0$
#164
1$
b01001000 '
b01001100 (
b01001000 )
#165
0$
#166
1$
b01001100 '
b01010000 (
b01001100 )
#167
0$
#168
1$
b01010000 '
b01010100 (
b01010000 )
#169
0$
#170
1$
b01010100 '
b01011000 (
b01010100 )
#171
0$
#172
1$
b01011000 '
b01011100 (
b01011000 )
#173
0$
#174
1$
b01011100 '
b01100000 (
b01011100 )
#175
0$
#176
1$
b01100000 '
b01100100 (
b01100000 )
#177
0$
#178
1$
b01100100 '
b01101000 (
b01100100 )
#179
0$
#180
1$
b01101000 '
b01101100 (
b01101000 )
#181
0$
#182
1$
b01101100 '
b01110000 (
b01101100 )
#183
0$
#184
1$
b01110000 '
b01110100 (
b01110000 )
#185
0$
#186
1$
b01110100 '
b01111000 (
b01110100 )
#187
0$
#188
1$
b01111000 '
b01111100 (
b01111000 )
#189
0$
#190
1$
b01111100 '
b10000000 (
b01111100 )
#191
0$
#192
1$
b10000000 '
b10000100 (
b10000000 )
#193
0$
#194
1$
b10000100 '
b10001000 (
b10000100 )
#195
0$
#196
1$
b10001000 '
b10001100 (
b10001000 )
#197
0$
#198
1$
b10001100 '
b10010000 (
b10001100 )
#199
0$
#200
1$
b10010000 '
b10010100 (
b10010000 )
#201
b00101010 #
0$
#202
1$
b10010100 '
b10011000 (
b10010100 )
#203
0$
#204
1$
b10011000 '
b10011100 (
b10011000 )
#205
0$
#206
1$
b10011100 '
b10100000 (
b10011100 )
#207
0$
#208
1$
b10100000 '
b10100100 (
b10100000 )
#209
0$
#210
1$
b10100100 '
b10101000 (
b10100100 )
#211
0$
#212
1$
b10101000 '
b10101100 (
b10101000 )
#213
0$
#214
1$
b10101100 '
b10110000 (
b10101100 )
#215
0$
#216
1$
b10110000 '
b10110100 (
b10110000 )
#217
0$
#218
1$
b10110100 '
b10111000 (
b10110100 )
#219
0$
#220
1$
b10111000 '
b10111100 (
b10111000 )
#221
0$
#222
1$
b10111100 '
b11000000 (
b10111100 )
#223
0$
#224
1$
b11000000 '
b11000100 (
b11000000 )
#225
0$
#226
1$
b11000100 '
b11001000 (
b11000100 )
#227
0$
#228
1$
b11001000 '
b11001100 (
b11001000 )
#229
0$
#230
1$
b11001100 '
b11010000 (
b11001100 )
#231
0$
#232
1$
b11010000 '
b11010100 (
b11010000 )
#233
0$
#234
1$
b11010100 '
b11011000 (
b11010100 )
#235
0$
#236
1$
b11011000 '
b11011100 (
b11011000 )
#237
0$
#238
1$
b11011100 '
b11100000 (
b11011100 )
#239
0$
#240
1$
b11100000 '
b11100100 (
b11100000 )
#241
0$
#242
1$
b11100100 '
b11101000 (
b11100100 )
#243
0$
#244
1$
b11101000 '
b11101100 (
b11101000 )
#245
0$
#246
1$
b11101100 '
b11110000 (
b11101100 )
#247
0$
#248
1$
b11110000 '
b11110100 (
b11110000 )
#249
0$
#250
1$
b11110100 '
b11111000 (
b11110100 )
#251
0$
#252
1$
b11111000 '
b11111100 (
b11111000 )
#253
0$
#254
1$
b11111100 '
b00000000 (
b11111100 )
#255
0$
#256
1$
b00000000 '
b00000100 (
b00000000 )
#257
0$
#258
1$
b00000100 '
b00001000 (
b00000100 )
#259
0$
#260
1$
b00001000 '
b00001100 (
b00001000 )
#261
0$
#262
1$
b00001100 '
b00010000 (
b00001100 )
#263
0$
#264
1$
b00010000 '
b00010100 (
b00010000 )
#265
0$
#266
1$
b00010100 '
b00011000 (
b00010100 )
#267
0$
#268
1$
b00011000 '
b00011100 (
b00011000 )
#269
0$
#270
1$
b00011100 '
b00100000 (
b00011100 )
#271
0$
#272
1$
b00100000 '
b00100100 (
b00100000 )
#273
0$
#274
1$
b00100100 '
b00101000 (
b00100100 )
#275
0$
#276
1$
b00101000 '
b00101100 (
b00101000 )
#277
0$
#278
1$
b00101100 '
b00110000 (
b00101100 )
#279
0$
#280
1$
b00110000 '
b00110100 (
b00110000 )
#281
0$
#282
1$
b00110100 '
b00111000 (
b00110100 )
#283
0$
#284
1$
b00111000 '
b00111100 (
b00111000 )
#285
0$
#286
1$
b00111100 '
b01000000 (
b00111100 )
#287
0$
#288
1$
b01000000 '
b01000100 (
b01000000 )
#289
0$
#290
1$
b01000100 '
b01001000 (
b01000100 )
#291
0$
#292
1$
b01001000 '
b01001100 (
b01001000 )
#293
0$
#294
1$
b01001100 '
b01010000 (
b01001100 )
#295
0$
#296
1$
b01010000 '
b01010100 (
b01010000 )
#297
0$
#298
1$
b01010100 '
b01011000 (
b01010100 )
#299
0$
#300
1$
b01011000 '
b01011100 (
b01011000 )
#301
0$
#302
1$
1%
b01011100 '
b01100000 (
b01011100 )
#303
0$
#304
1$
0%
b00000000 '
b00000100 (
b00000000 )
#305
0$
#306
1$
b00000100 '
b00001000 (
b00000100 )
#307
0$
#308
1$
b00001000 '
b00001100 (
b00001000 )
#309
0$
#310
1$
b00001100 '
b00010000 (
b00001100 )
#311
0$
#312
1$
b00010000 '
b00010100 (
b00010000 )
#313
0$
#314
1$
b00010100 '
b00011000 (
b00010100 )
#315
0$
#316
1$
b00011000 '
b00011100 (
b00011000 )
#317
0$
#318
1$
b00011100 '
b00100000 (
b00011100 )
#319
0$
#320
1$
b00100000 '
b00100100 (
b00100000 )
#321
0$
#322
1$
b00100100 '
b00101000 (
b00100100 )
#323
0$
#324
1$
b00101000 '
b00101100 (
b00101000 )
#325
0$
#326
1$
b00101100 '
b00110000 (
b00101100 )
#327
0$
#328
1$
b00110000 '
b00110100 (
b00110000 )
#329
0$
#330
1$
b00110100 '
b00111000 (
b00110100 )
#331
0$
#332
1$
b00111000 '
b00111100 (
b00111000 )
#333
0$
#334
1$
b00111100 '
b01000000 (
b00111100 )
#335
0$
#336
1$
b01000000 '
b01000100 (
b01000000 )
#337
0$
#338
1$
b01000100 '
b01001000 (
b01000100 )
#339
0$
#340
1$
b01001000 '
b01001100 (
b01001000 )
#341
0$
#342
1$
b01001100 '
b01010000 (
b01001100 )
#343
0$
#344
1$
b01010000 '
b01010100 (
b01010000 )
#345
0$
#346
1$
b01010100 '
b01011000 (
b01010100 )
#347
0$
#348
1$
b01011000 '
b01011100 (
b01011000 )
#349
0$
#350
1$
b01011100 '
b01100000 (
b01011100 )
#351
0$
#352
1$
1&
b01100000 '
b10001010 (
b01100000 )
#353
0$
#354
1$
0&
b10001010 '
b10001110 (
b10001010 )
#355
0$
#356
1$
b10001110 '
b10010010 (
b10001110 )
#357
0$
#358
1$
b10010010 '
b10010110 (
b10010010 )
#359
0$
#360
1$
b10010110 '
b10011010 (
b10010110 )
#361
0$
#362
1$
b10011010 '
b10011110 (
b10011010 )
#363
0$
#364
1$
b10011110 '
b10100010 (
b10011110 )
#365
0$
#366
1$
b10100010 '
b10100110 (
b10100010 )
#367
0$
#368
1$
b10100110 '
b10101010 (
b10100110 )
#369
0$
#370
1$
b10101010 '
b10101110 (
b10101010 )
#371
0$
#372
1$
b10101110 '
b10110010 (
b10101110 )
#373
0$
#374
1$
b10110010 '
b10110110 (
b10110010 )
#375
0$
#376
1$
b10110110 '
b10111010 (
b10110110 )
#377
0$
#378
1$
b10111010 '
b10111110 (
b10111010 )
#379
0$
#380
1$
b10111110 '
b11000010 (
b10111110 )
#381
0$
#382
1$
b11000010 '
b11000110 (
b11000010 )
#383
0$
#384
1$
b11000110 '
b11001010 (
b11000110 )
#385
0$
#386
1$
b11001010 '
b11001110 (
b11001010 )
#387
0$
#388
1$
b11001110 '
b11010010 (
b11001110 )
#389
0$
#390
1$
b11010010 '
b11010110 (
b11010010 )
#391
0$
#392
1$
b11010110 '
b11011010 (
b11010110 )
#393
0$
#394
1$
b11011010 '
b11011110 (
b11011010 )
#395
0$
#396
1$
b11011110 '
b11100010 (
b11011110 )
#397
0$
#398
1$
b11100010 '
b11100110 (
b11100010 )
#399
0$
#400
1$
b11100110 '
b11101010 (
b11100110 )
#401
0$
#402
1$
b11101010 '
b11101110 (
b11101010 )
#403
0$
#404
1$
b11101110 '
b11110010 (
b11101110 )
#405
0$
#406
1$
b11110010 '
b11110110 (
b11110010 )
#407
0$
#408
1$
b11110110 '
b11111010 (
b11110110 )
#409
0$
#410
1$
b11111010 '
b11111110 (
b11111010 )
#411
0$
#412
1$
b11111110 '
b00000010 (
b11111110 )
#413
0$
#414
1$
b00000010 '
b00000110 (
b00000010 )
#415
0$
#416
1$
b00000110 '
b00001010 (
b00000110 )
#417
0$
#418
1$
b00001010 '
b00001110 (
b00001010 )
#419
0$
#420
1$
b00001110 '
b00010010 (
b00001110 )
#421
0$
#422
1$
b00010010 '
b00010110 (
b00010010 )
#423
0$
#424
1$
b00010110 '
b00011010 (
b00010110 )
#425
0$
#426
1$
b00011010 '
b00011110 (
b00011010 )
#427
0$
#428
1$
b00011110 '
b00100010 (
b00011110 )
#429
0$
#430
1$
b00100010 '
b00100110 (
b00100010 )
#431
0$
#432
1$
b00100110 '
b00101010 (
b00100110 )
#433
0$
#434
1$
b00101010 '
b00101110 (
b00101010 )
#435
0$
#436
1$
b00101110 '
b00110010 (
b00101110 )
#437
0$
#438
1$
b00110010 '
b00110110 (
b00110010 )
#439
0$
#440
1$
b00110110 '
b00111010 (
b00110110 )
#441
0$
#442
1$
b00111010 '
b00111110 (
b00111010 )
#443
0$
#444
1$
b00111110 '
b01000010 (
b00111110 )
#445
0$
#446
1$
b01000010 '
b01000110 (
b01000010 )
#447
0$
#448
1$
b01000110 '
b01001010 (
b01000110 )
#449
0$
#450
1$
b01001010 '
b01001110 (
b01001010 )
#451
0$
#452
1$
b01001110 '
b01010010 (
b01001110 )
#453
0$
#454
1$
b01010010 '
b01010110 (
b01010010 )
#455
0$
#456
1$
b01010110 '
b01011010 (
b01010110 )
#457
0$
#458
1$
b01011010 '
b01011110 (
b01011010 )
#459
0$
#460
1$
b01011110 '
b01100010 (
b01011110 )
#461
0$
#462
1$
b01100010 '
b01100110 (
b01100010 )
#463
0$
#464
1$
b01100110 '
b01101010 (
b01100110 )
#465
0$
#466
1$
b01101010 '
b01101110 (
b01101010 )
#467
0$
#468
1$
b01101110 '
b01110010 (
b01101110 )
#469
0$
#470
1$
b01110010 '
b01110110 (
b01110010 )
#471
0$
#472
1$
b01110110 '
b01111010 (
b01110110 )
#473
0$
#474
1$
b01111010 '
b01111110 (
b01111010 )
#475
0$
#476
1$
b01111110 '
b10000010 (
b01111110 )
#477
0$
#478
1$
b10000010 '
b10000110 (
b10000010 )
#479
0$
#480
1$
b10000110 '
b10001010 (
b10000110 )
#481
0$
#482
1$
b10001010 '
b10001110 (
b10001010 )
#483
0$
#484
1$
b10001110 '
b10010010 (
b10001110 )
#485
0$
#486
1$
b10010010 '
b10010110 (
b10010010 )
#487
0$
#488
1$
b10010110 '
b10011010 (
b10010110 )
#489
0$
#490
1$
b10011010 '
b10011110 (
b10011010 )
#491
0$
#492
1$
b10011110 '
b10100010 (
b10011110 )
#493
0$
#494
1$
b10100010 '
b10100110 (
b10100010 )
#495
0$
#496
1$
b10100110 '
b10101010 (
b10100110 )
#497
0$
#498
1$
b10101010 '
b10101110 (
b10101010 )
#499
0$
#500
1$
b10101110 '
b10110010 (
b10101110 )
#501
0$
#502
1$
b10110010 '
b10110110 (
b10110010 )
#503
0$
#504
1$
b10110110 '
b10111010 (
b10110110 )
#505
0$
#506
1$
b10111010 '
b10111110 (
b10111010 )
#507
0$
#508
1$
b10111110 '
b11000010 (
b10111110 )
#509
0$
#510
1$
b11000010 '
b11000110 (
b11000010 )
#511
0$
#512
1$
b11000110 '
b11001010 (
b11000110 )
#513
0$
#514
1$
b11001010 '
b11001110 (
b11001010 )
#515
0$
#516
1$
b11001110 '
b11010010 (
b11001110 )
#517
0$
#518
1$
b11010010 '
b11010110 (
b11010010 )
#519
0$
#520
1$
b11010110 '
b11011010 (
b11010110 )
#521
0$
#522
1$
b11011010 '
b11011110 (
b11011010 )
#523
0$
#524
1$
b11011110 '
b11100010 (
b11011110 )
#525
0$
#526
1$
b11100010 '
b11100110 (
b11100010 )
#527
0$
#528
1$
b11100110 '
b11101010 (
b11100110 )
#529
0$
#530
1$
b11101010 '
b11101110 (
b11101010 )
#531
0$
#532
1$
b11101110 '
b11110010 (
b11101110 )
#533
0$
#534
1$
b11110010 '
b11110110 (
b11110010 )
#535
0$
#536
1$
b11110110 '
b11111010 (
b11110110 )
#537
0$
#538
1$
b11111010 '
b11111110 (
b11111010 )
#539
0$
#540
1$
b11111110 '
b00000010 (
b11111110 )
#541
0$
#542
1$
b00000010 '
b00000110 (
b00000010 )
#543
0$
#544
1$
b00000110 '
b00001010 (
b00000110 )
#545
0$
#546
1$
b00001010 '
b00001110 (
b00001010 )
#547
0$
#548
1$
b00001110 '
b00010010 (
b00001110 )
#549
0$
#550
1$
b00010010 '
b00010110 (
b00010010 )
#551
0$
#552
1$
b00010110 '
b00011010 (
b00010110 )
#553
0$
#554
1$
b00011010 '
b00011110 (
b00011010 )
#555
0$
#556
1$
b00011110 '
b00100010 (
b00011110 )
#557
0$
#558
1$
b00100010 '
b00100110 (
b00100010 )
#559
0$
#560
1$
b00100110 '
b00101010 (
b00100110 )
#561
0$
#562
1$
b00101010 '
b00101110 (
b00101010 )
#563
0$
#564
1$
b00101110 '
b00110010 (
b00101110 )
#565
0$
#566
1$
b00110010 '
b00110110 (
b00110010 )
#567
0$
#568
1$
b00110110 '
b00111010 (
b00110110 )
#569
0$
#570
1$
b00111010 '
b00111110 (
b00111010 )
#571
0$
#572
1$
b00111110 '
b01000010 (
b00111110 )
#573
0$
#574
1$
b01000010 '
b01000110 (
b01000010 )
#575
0$
#576
1$
b01000110 '
b01001010 (
b01000110 )
#577
0$
#578
1$
b01001010 '
b01001110 (
b01001010 )
#579
0$
#580
1$
b01001110 '
b01010010 (
b01001110 )
#581
0$
#582
1$
b01010010 '
b01010110 (
b01010010 )
#583
0$
#584
1$
b01010110 '
b01011010 (
b01010110 )
#585
0$
#586
1$
b01011010 '
b01011110 (
b01011010 )
#587
0$
#588
1$
b01011110 '
b01100010 (
b01011110 )
#589
0$
#590
1$
b01100010 '
b01100110 (
b01100010 )
#591
0$
#592
1$
b01100110 '
b01101010 (
b01100110 )
#593
0$
#594
1$
b01101010 '
b01101110 (
b01101010 )
#595
0$
#596
1$
b01101110 '
b01110010 (
b01101110 )
#597
0$
#598
1$
b01110010 '
b01110110 (
b01110010 )
