src/PC/register.sv
module register#(
    parameter WIDTH = 32
)(
    input   logic   clk,
    input   logic   rst,
    input   logic [WIDTH-1:0]   next_PC,
    output  logic [WIDTH-1:0]   PC
);

reg [WIDTH-1:0] current_PC;

always_ff @ (posedge clk)
    if (rst) current_PC <= {WIDTH{1'b0}};
    else current_PC <= next_PC;

assign PC = current_PC;
endmodule

src/PC/PC.sv
module PC #(
    parameter WIDTH = 32
) (
    input   logic [WIDTH-1:0]   ImmOp,
    input   logic               clk,
    input   logic               rst,
    input   logic               jmp_sel,
    output  logic [WIDTH-1:0]   PC_OUT
);

logic [WIDTH-1:0] branch_PC;
logic [WIDTH-1:0] current_PC;

register PCReg (
    .PC(current_PC),
    .next_PC(branch_PC),
    .clk(clk),
    .rst(rst)
);

always_comb begin
    branch_PC = (jmp_sel) ? current_PC+ImmOp:current_PC+4;
end

assign PC_OUT = current_PC;
endmodule

src/PC/test1.vcd
$version Generated by VerilatedVcd $end
$date Fri Nov 18 12:53:32 2022 $end
$timescale 1ps $end

 $scope module TOP $end
  $var wire  8 # ImmOp [7:0] $end
  $var wire  8 ' PC_OUT [7:0] $end
  $var wire  1 $ clk $end
  $var wire  1 & jmp_sel $end
  $var wire  1 % rst $end
  $scope module PC $end
   $var wire  8 # ImmOp [7:0] $end
   $var wire  8 ' PC_OUT [7:0] $end
   $var wire 32 * WIDTH [31:0] $end
   $var wire  8 ( branch_PC [7:0] $end
   $var wire  1 $ clk $end
   $var wire  8 ) current_PC [7:0] $end
   $var wire  1 & jmp_sel $end
   $var wire  1 % rst $end
   $scope module PCReg $end
    $var wire  8 ) PC [7:0] $end
    $var wire 32 * WIDTH [31:0] $end
    $var wire  1 $ clk $end
    $var wire  8 ) current_PC [7:0] $end
    $var wire  8 ( next_PC [7:0] $end
    $var wire  1 % rst $end
   $upscope $end
  $upscope $end
 $upscope $end
$enddefinitions $end


#0
b00000000 #
0$
0%
0&
b00000000 '
b00000100 (
b00000000 )
b00000000000000000000000000001000 *
#1
1$
#2
0$
#3
1$
b00000100 '
b00001000 (
b00000100 )
#4
0$
#5
1$
b00001000 '
b00001100 (
b00001000 )
#6
0$
#7
1$
b00001100 '
b00010000 (
b00001100 )
#8
0$
#9
1$
b00010000 '
b00010100 (
b00010000 )
#10
0$
#11
1$
b00010100 '
b00011000 (
b00010100 )
#12
0$
#13
1$
b00011000 '
b00011100 (
b00011000 )
#14
0$
#15
1$
b00011100 '
b00100000 (
b00011100 )
#16
0$
#17
1$
b00100000 '
b00100100 (
b00100000 )
#18
0$
#19
1$
b00100100 '
b00101000 (
b00100100 )
#20
0$
#21
1$
b00101000 '
b00101100 (
b00101000 )
#22
0$
#23
1$
b00101100 '
b00110000 (
b00101100 )
#24
0$
#25
1$
b00110000 '
b00110100 (
b00110000 )
#26
0$
#27
1$
b00110100 '
b00111000 (
b00110100 )
#28
0$
#29
1$
b00111000 '
b00111100 (
b00111000 )
#30
0$
#31
1$
b00111100 '
b01000000 (
b00111100 )
#32
0$
#33
1$
b01000000 '
b01000100 (
b01000000 )
#34
0$
#35
1$
b01000100 '
b01001000 (
b01000100 )
#36
0$
#37
1$
b01001000 '
b01001100 (
b01001000 )
#38
0$
#39
1$
b01001100 '
b01010000 (
b01001100 )
#40
0$
#41
1$
b01010000 '
b01010100 (
b01010000 )
#42
0$
#43
1$
b01010100 '
b01011000 (
b01010100 )
#44
0$
#45
1$
b01011000 '
b01011100 (
b01011000 )
#46
0$
#47
1$
b01011100 '
b01100000 (
b01011100 )
#48
0$
#49
1$
b01100000 '
b01100100 (
b01100000 )
#50
0$
#51
1$
b01100100 '
b01101000 (
b01100100 )
#52
0$
#53
1$
b01101000 '
b01101100 (
b01101000 )
#54
0$
#55
1$
b01101100 '
b01110000 (
b01101100 )
#56
0$
#57
1$
b01110000 '
b01110100 (
b01110000 )
#58
0$
#59
1$
b01110100 '
b01111000 (
b01110100 )
#60
0$
#61
1$
b01111000 '
b01111100 (
b01111000 )
#62
0$
#63
1$
b01111100 '
b10000000 (
b01111100 )
#64
0$
#65
1$
b10000000 '
b10000100 (
b10000000 )
#66
0$
#67
1$
b10000100 '
b10001000 (
b10000100 )
#68
0$
#69
1$
b10001000 '
b10001100 (
b10001000 )
#70
0$
#71
1$
b10001100 '
b10010000 (
b10001100 )
#72
0$
#73
1$
b10010000 '
b10010100 (
b10010000 )
#74
0$
#75
1$
b10010100 '
b10011000 (
b10010100 )
#76
0$
#77
1$
b10011000 '
b10011100 (
b10011000 )
#78
0$
#79
1$
b10011100 '
b10100000 (
b10011100 )
#80
0$
#81
1$
b10100000 '
b10100100 (
b10100000 )
#82
0$
#83
1$
b10100100 '
b10101000 (
b10100100 )
#84
0$
#85
1$
b10101000 '
b10101100 (
b10101000 )
#86
0$
#87
1$
b10101100 '
b10110000 (
b10101100 )
#88
0$
#89
1$
b10110000 '
b10110100 (
b10110000 )
#90
0$
#91
1$
b10110100 '
b10111000 (
b10110100 )
#92
0$
#93
1$
b10111000 '
b10111100 (
b10111000 )
#94
0$
#95
1$
b10111100 '
b11000000 (
b10111100 )
#96
0$
#97
1$
b11000000 '
b11000100 (
b11000000 )
#98
0$
#99
1$
b11000100 '
b11001000 (
b11000100 )
#100
0$
#101
1$
b11001000 '
b11001100 (
b11001000 )
#102
0$
#103
1$
b11001100 '
b11010000 (
b11001100 )
#104
0$
#105
1$
b11010000 '
b11010100 (
b11010000 )
#106
0$
#107
1$
b11010100 '
b11011000 (
b11010100 )
#108
0$
#109
1$
b11011000 '
b11011100 (
b11011000 )
#110
0$
#111
1$
b11011100 '
b11100000 (
b11011100 )
#112
0$
#113
1$
b11100000 '
b11100100 (
b11100000 )
#114
0$
#115
1$
b11100100 '
b11101000 (
b11100100 )
#116
0$
#117
1$
b11101000 '
b11101100 (
b11101000 )
#118
0$
#119
1$
b11101100 '
b11110000 (
b11101100 )
#120
0$
#121
1$
b11110000 '
b11110100 (
b11110000 )
#122
0$
#123
1$
b11110100 '
b11111000 (
b11110100 )
#124
0$
#125
1$
b11111000 '
b11111100 (
b11111000 )
#126
0$
#127
1$
b11111100 '
b00000000 (
b11111100 )
#128
0$
#129
1$
b00000000 '
b00000100 (
b00000000 )
#130
0$
#131
1$
b00000100 '
b00001000 (
b00000100 )
#132
0$
#133
1$
b00001000 '
b00001100 (
b00001000 )
#134
0$
#135
1$
b00001100 '
b00010000 (
b00001100 )
#136
0$
#137
1$
b00010000 '
b00010100 (
b00010000 )
#138
0$
#139
1$
b00010100 '
b00011000 (
b00010100 )
#140
0$
#141
1$
b00011000 '
b00011100 (
b00011000 )
#142
0$
#143
1$
b00011100 '
b00100000 (
b00011100 )
#144
0$
#145
1$
b00100000 '
b00100100 (
b00100000 )
#146
0$
#147
1$
b00100100 '
b00101000 (
b00100100 )
#148
0$
#149
1$
b00101000 '
b00101100 (
b00101000 )
#150
0$
#151
1$
b00101100 '
b00110000 (
b00101100 )
#152
0$
#153
1$
b00110000 '
b00110100 (
b00110000 )
#154
0$
#155
1$
b00110100 '
b00111000 (
b00110100 )
#156
0$
#157
1$
b00111000 '
b00111100 (
b00111000 )
#158
0$
#159
1$
b00111100 '
b01000000 (
b00111100 )
#160
0$
#161
1$
b01000000 '
b01000100 (
b01000000 )
#162
0$
#163
1$
b01000100 '
b01001000 (
b01000100 )
#164
0$
#165
1$
b01001000 '
b01001100 (
b01001000 )
#166
0$
#167
1$
b01001100 '
b01010000 (
b01001100 )
#168
0$
#169
1$
b01010000 '
b01010100 (
b01010000 )
#170
0$
#171
1$
b01010100 '
b01011000 (
b01010100 )
#172
0$
#173
1$
b01011000 '
b01011100 (
b01011000 )
#174
0$
#175
1$
b01011100 '
b01100000 (
b01011100 )
#176
0$
#177
1$
b01100000 '
b01100100 (
b01100000 )
#178
0$
#179
1$
b01100100 '
b01101000 (
b01100100 )
#180
0$
#181
1$
b01101000 '
b01101100 (
b01101000 )
#182
0$
#183
1$
b01101100 '
b01110000 (
b01101100 )
#184
0$
#185
1$
b01110000 '
b01110100 (
b01110000 )
#186
0$
#187
1$
b01110100 '
b01111000 (
b01110100 )
#188
0$
#189
1$
b01111000 '
b01111100 (
b01111000 )
#190
0$
#191
1$
b01111100 '
b10000000 (
b01111100 )
#192
0$
#193
1$
b10000000 '
b10000100 (
b10000000 )
#194
0$
#195
1$
b10000100 '
b10001000 (
b10000100 )
#196
0$
#197
1$
b10001000 '
b10001100 (
b10001000 )
#198
0$
#199
1$
b10001100 '
b10010000 (
b10001100 )
#200
0$
#201
1$
b10010000 '
b10010100 (
b10010000 )
#202
0$
#203
1$
b10010100 '
b10011000 (
b10010100 )
#204
0$
#205
1$
b10011000 '
b10011100 (
b10011000 )
#206
0$
#207
1$
b10011100 '
b10100000 (
b10011100 )
#208
0$
#209
1$
b10100000 '
b10100100 (
b10100000 )
#210
0$
#211
1$
b10100100 '
b10101000 (
b10100100 )
#212
0$
#213
1$
b10101000 '
b10101100 (
b10101000 )
#214
0$
#215
1$
b10101100 '
b10110000 (
b10101100 )
#216
0$
#217
1$
b10110000 '
b10110100 (
b10110000 )
#218
0$
#219
1$
b10110100 '
b10111000 (
b10110100 )
#220
0$
#221
1$
b10111000 '
b10111100 (
b10111000 )
#222
0$
#223
1$
b10111100 '
b11000000 (
b10111100 )
#224
0$
#225
1$
b11000000 '
b11000100 (
b11000000 )
#226
0$
#227
1$
b11000100 '
b11001000 (
b11000100 )
#228
0$
#229
1$
b11001000 '
b11001100 (
b11001000 )
#230
0$
#231
1$
b11001100 '
b11010000 (
b11001100 )
#232
0$
#233
1$
b11010000 '
b11010100 (
b11010000 )
#234
0$
#235
1$
b11010100 '
b11011000 (
b11010100 )
#236
0$
#237
1$
b11011000 '
b11011100 (
b11011000 )
#238
0$
#239
1$
b11011100 '
b11100000 (
b11011100 )
#240
0$
#241
1$
b11100000 '
b11100100 (
b11100000 )
#242
0$
#243
1$
b11100100 '
b11101000 (
b11100100 )
#244
0$
#245
1$
b11101000 '
b11101100 (
b11101000 )
#246
0$
#247
1$
b11101100 '
b11110000 (
b11101100 )
#248
0$
#249
1$
b11110000 '
b11110100 (
b11110000 )
#250
0$
#251
1$
b11110100 '
b11111000 (
b11110100 )
#252
0$
#253
1$
b11111000 '
b11111100 (
b11111000 )
#254
0$
#255
1$
b11111100 '
b00000000 (
b11111100 )
#256
0$
#257
1$
b00000000 '
b00000100 (
b00000000 )
#258
0$
#259
1$
b00000100 '
b00001000 (
b00000100 )
#260
0$
#261
1$
b00001000 '
b00001100 (
b00001000 )
#262
0$
#263
1$
b00001100 '
b00010000 (
b00001100 )
#264
0$
#265
1$
b00010000 '
b00010100 (
b00010000 )
#266
0$
#267
1$
b00010100 '
b00011000 (
b00010100 )
#268
0$
#269
1$
b00011000 '
b00011100 (
b00011000 )
#270
0$
#271
1$
b00011100 '
b00100000 (
b00011100 )
#272
0$
#273
1$
b00100000 '
b00100100 (
b00100000 )
#274
0$
#275
1$
b00100100 '
b00101000 (
b00100100 )
#276
0$
#277
1$
b00101000 '
b00101100 (
b00101000 )
#278
0$
#279
1$
b00101100 '
b00110000 (
b00101100 )
#280
0$
#281
1$
b00110000 '
b00110100 (
b00110000 )
#282
0$
#283
1$
b00110100 '
b00111000 (
b00110100 )
#284
0$
#285
1$
b00111000 '
b00111100 (
b00111000 )
#286
0$
#287
1$
b00111100 '
b01000000 (
b00111100 )
#288
0$
#289
1$
b01000000 '
b01000100 (
b01000000 )
#290
0$
#291
1$
b01000100 '
b01001000 (
b01000100 )
#292
0$
#293
1$
b01001000 '
b01001100 (
b01001000 )
#294
0$
#295
1$
b01001100 '
b01010000 (
b01001100 )
#296
0$
#297
1$
b01010000 '
b01010100 (
b01010000 )
#298
0$
#299
1$
b01010100 '
b01011000 (
b01010100 )
#300
0$
#301
1$
b01011000 '
b01011100 (
b01011000 )
#302
0$
#303
1$
b01011100 '
b01100000 (
b01011100 )
#304
0$
#305
1$
b01100000 '
b01100100 (
b01100000 )
#306
0$
#307
1$
b01100100 '
b01101000 (
b01100100 )
#308
0$
#309
1$
b01101000 '
b01101100 (
b01101000 )
#310
0$
#311
1$
b01101100 '
b01110000 (
b01101100 )
#312
0$
#313
1$
b01110000 '
b01110100 (
b01110000 )
#314
0$
#315
1$
b01110100 '
b01111000 (
b01110100 )
#316
0$
#317
1$
b01111000 '
b01111100 (
b01111000 )
#318
0$
#319
1$
b01111100 '
b10000000 (
b01111100 )
#320
0$
#321
1$
b10000000 '
b10000100 (
b10000000 )
#322
0$
#323
1$
b10000100 '
b10001000 (
b10000100 )
#324
0$
#325
1$
b10001000 '
b10001100 (
b10001000 )
#326
0$
#327
1$
b10001100 '
b10010000 (
b10001100 )
#328
0$
#329
1$
b10010000 '
b10010100 (
b10010000 )
#330
0$
#331
1$
b10010100 '
b10011000 (
b10010100 )
#332
0$
#333
1$
b10011000 '
b10011100 (
b10011000 )
#334
0$
#335
1$
b10011100 '
b10100000 (
b10011100 )
#336
0$
#337
1$
b10100000 '
b10100100 (
b10100000 )
#338
0$
#339
1$
b10100100 '
b10101000 (
b10100100 )
#340
0$
#341
1$
b10101000 '
b10101100 (
b10101000 )
#342
0$
#343
1$
b10101100 '
b10110000 (
b10101100 )
#344
0$
#345
1$
b10110000 '
b10110100 (
b10110000 )
#346
0$
#347
1$
b10110100 '
b10111000 (
b10110100 )
#348
0$
#349
1$
b10111000 '
b10111100 (
b10111000 )
#350
0$
#351
1$
b10111100 '
b11000000 (
b10111100 )
#352
0$
#353
1$
b11000000 '
b11000100 (
b11000000 )
#354
0$
#355
1$
b11000100 '
b11001000 (
b11000100 )
#356
0$
#357
1$
b11001000 '
b11001100 (
b11001000 )
#358
0$
#359
1$
b11001100 '
b11010000 (
b11001100 )
#360
0$
#361
1$
b11010000 '
b11010100 (
b11010000 )
#362
0$
#363
1$
b11010100 '
b11011000 (
b11010100 )
#364
0$
#365
1$
b11011000 '
b11011100 (
b11011000 )
#366
0$
#367
1$
b11011100 '
b11100000 (
b11011100 )
#368
0$
#369
1$
b11100000 '
b11100100 (
b11100000 )
#370
0$
#371
1$
b11100100 '
b11101000 (
b11100100 )
#372
0$
#373
1$
b11101000 '
b11101100 (
b11101000 )
#374
0$
#375
1$
b11101100 '
b11110000 (
b11101100 )
#376
0$
#377
1$
b11110000 '
b11110100 (
b11110000 )
#378
0$
#379
1$
b11110100 '
b11111000 (
b11110100 )
#380
0$
#381
1$
b11111000 '
b11111100 (
b11111000 )
#382
0$
#383
1$
b11111100 '
b00000000 (
b11111100 )
#384
0$
#385
1$
b00000000 '
b00000100 (
b00000000 )
#386
0$
#387
1$
b00000100 '
b00001000 (
b00000100 )
#388
0$
#389
1$
b00001000 '
b00001100 (
b00001000 )
#390
0$
#391
1$
b00001100 '
b00010000 (
b00001100 )
#392
0$
#393
1$
b00010000 '
b00010100 (
b00010000 )
#394
0$
#395
1$
b00010100 '
b00011000 (
b00010100 )
#396
0$
#397
1$
b00011000 '
b00011100 (
b00011000 )
#398
0$
#399
1$
b00011100 '
b00100000 (
b00011100 )
#400
0$
#401
1$
b00100000 '
b00100100 (
b00100000 )
#402
0$
#403
1$
b00100100 '
b00101000 (
b00100100 )
#404
0$
#405
1$
b00101000 '
b00101100 (
b00101000 )
#406
0$
#407
1$
b00101100 '
b00110000 (
b00101100 )
#408
0$
#409
1$
b00110000 '
b00110100 (
b00110000 )
#410
0$
#411
1$
b00110100 '
b00111000 (
b00110100 )
#412
0$
#413
1$
b00111000 '
b00111100 (
b00111000 )
#414
0$
#415
1$
b00111100 '
b01000000 (
b00111100 )
#416
0$
#417
1$
b01000000 '
b01000100 (
b01000000 )
#418
0$
#419
1$
b01000100 '
b01001000 (
b01000100 )
#420
0$
#421
1$
b01001000 '
b01001100 (
b01001000 )
#422
0$
#423
1$
b01001100 '
b01010000 (
b01001100 )
#424
0$
#425
1$
b01010000 '
b01010100 (
b01010000 )
#426
0$
#427
1$
b01010100 '
b01011000 (
b01010100 )
#428
0$
#429
1$
b01011000 '
b01011100 (
b01011000 )
#430
0$
#431
1$
b01011100 '
b01100000 (
b01011100 )
#432
0$
#433
1$
b01100000 '
b01100100 (
b01100000 )
#434
0$
#435
1$
b01100100 '
b01101000 (
b01100100 )
#436
0$
#437
1$
b01101000 '
b01101100 (
b01101000 )
#438
0$
#439
1$
b01101100 '
b01110000 (
b01101100 )
#440
0$
#441
1$
b01110000 '
b01110100 (
b01110000 )
#442
0$
#443
1$
b01110100 '
b01111000 (
b01110100 )
#444
0$
#445
1$
b01111000 '
b01111100 (
b01111000 )
#446
0$
#447
1$
b01111100 '
b10000000 (
b01111100 )
#448
0$
#449
1$
b10000000 '
b10000100 (
b10000000 )
#450
0$
#451
1$
b10000100 '
b10001000 (
b10000100 )
#452
0$
#453
1$
b10001000 '
b10001100 (
b10001000 )
#454
0$
#455
1$
b10001100 '
b10010000 (
b10001100 )
#456
0$
#457
1$
b10010000 '
b10010100 (
b10010000 )
#458
0$
#459
1$
b10010100 '
b10011000 (
b10010100 )
#460
0$
#461
1$
b10011000 '
b10011100 (
b10011000 )
#462
0$
#463
1$
b10011100 '
b10100000 (
b10011100 )
#464
0$
#465
1$
b10100000 '
b10100100 (
b10100000 )
#466
0$
#467
1$
b10100100 '
b10101000 (
b10100100 )
#468
0$
#469
1$
b10101000 '
b10101100 (
b10101000 )
#470
0$
#471
1$
b10101100 '
b10110000 (
b10101100 )
#472
0$
#473
1$
b10110000 '
b10110100 (
b10110000 )
#474
0$
#475
1$
b10110100 '
b10111000 (
b10110100 )
#476
0$
#477
1$
b10111000 '
b10111100 (
b10111000 )
#478
0$
#479
1$
b10111100 '
b11000000 (
b10111100 )
#480
0$
#481
1$
b11000000 '
b11000100 (
b11000000 )
#482
0$
#483
1$
b11000100 '
b11001000 (
b11000100 )
#484
0$
#485
1$
b11001000 '
b11001100 (
b11001000 )
#486
0$
#487
1$
b11001100 '
b11010000 (
b11001100 )
#488
0$
#489
1$
b11010000 '
b11010100 (
b11010000 )
#490
0$
#491
1$
b11010100 '
b11011000 (
b11010100 )
#492
0$
#493
1$
b11011000 '
b11011100 (
b11011000 )
#494
0$
#495
1$
b11011100 '
b11100000 (
b11011100 )
#496
0$
#497
1$
b11100000 '
b11100100 (
b11100000 )
#498
0$
#499
1$
b11100100 '
b11101000 (
b11100100 )
#500
0$
#501
1$
b11101000 '
b11101100 (
b11101000 )
#502
0$
#503
1$
b11101100 '
b11110000 (
b11101100 )
#504
0$
#505
1$
b11110000 '
b11110100 (
b11110000 )
#506
0$
#507
1$
b11110100 '
b11111000 (
b11110100 )
#508
0$
#509
1$
b11111000 '
b11111100 (
b11111000 )
#510
0$
#511
1$
b11111100 '
b00000000 (
b11111100 )
#512
0$
#513
1$
b00000000 '
b00000100 (
b00000000 )
#514
0$
#515
1$
b00000100 '
b00001000 (
b00000100 )
#516
0$
#517
1$
b00001000 '
b00001100 (
b00001000 )
#518
0$
#519
1$
b00001100 '
b00010000 (
b00001100 )
#520
0$
#521
1$
b00010000 '
b00010100 (
b00010000 )
#522
0$
#523
1$
b00010100 '
b00011000 (
b00010100 )
#524
0$
#525
1$
b00011000 '
b00011100 (
b00011000 )
#526
0$
#527
1$
b00011100 '
b00100000 (
b00011100 )
#528
0$
#529
1$
b00100000 '
b00100100 (
b00100000 )
#530
0$
#531
1$
b00100100 '
b00101000 (
b00100100 )
#532
0$
#533
1$
b00101000 '
b00101100 (
b00101000 )
#534
0$
#535
1$
b00101100 '
b00110000 (
b00101100 )
#536
0$
#537
1$
b00110000 '
b00110100 (
b00110000 )
#538
0$
#539
1$
b00110100 '
b00111000 (
b00110100 )
#540
0$
#541
1$
b00111000 '
b00111100 (
b00111000 )
#542
0$
#543
1$
b00111100 '
b01000000 (
b00111100 )
#544
0$
#545
1$
b01000000 '
b01000100 (
b01000000 )
#546
0$
#547
1$
b01000100 '
b01001000 (
b01000100 )
#548
0$
#549
1$
b01001000 '
b01001100 (
b01001000 )
#550
0$
#551
1$
b01001100 '
b01010000 (
b01001100 )
#552
0$
#553
1$
b01010000 '
b01010100 (
b01010000 )
#554
0$
#555
1$
b01010100 '
b01011000 (
b01010100 )
#556
0$
#557
1$
b01011000 '
b01011100 (
b01011000 )
#558
0$
#559
1$
b01011100 '
b01100000 (
b01011100 )
#560
0$
#561
1$
b01100000 '
b01100100 (
b01100000 )
#562
0$
#563
1$
b01100100 '
b01101000 (
b01100100 )
#564
0$
#565
1$
b01101000 '
b01101100 (
b01101000 )
#566
0$
#567
1$
b01101100 '
b01110000 (
b01101100 )
#568
0$
#569
1$
b01110000 '
b01110100 (
b01110000 )
#570
0$
#571
1$
b01110100 '
b01111000 (
b01110100 )
#572
0$
#573
1$
b01111000 '
b01111100 (
b01111000 )
#574
0$
#575
1$
b01111100 '
b10000000 (
b01111100 )
#576
0$
#577
1$
b10000000 '
b10000100 (
b10000000 )
#578
0$
#579
1$
b10000100 '
b10001000 (
b10000100 )
#580
0$
#581
1$
b10001000 '
b10001100 (
b10001000 )
#582
0$
#583
1$
b10001100 '
b10010000 (
b10001100 )
#584
0$
#585
1$
b10010000 '
b10010100 (
b10010000 )
#586
0$
#587
1$
b10010100 '
b10011000 (
b10010100 )
#588
0$
#589
1$
b10011000 '
b10011100 (
b10011000 )
#590
0$
#591
1$
b10011100 '
b10100000 (
b10011100 )
#592
0$
#593
1$
b10100000 '
b10100100 (
b10100000 )
#594
0$
#595
1$
b10100100 '
b10101000 (
b10100100 )
#596
0$
#597
1$
b10101000 '
b10101100 (
b10101000 )
#598
0$
#599
1$
b10101100 '
b10110000 (
b10101100 )
#600
0$
#601
1$
b10110000 '
b10110100 (
b10110000 )
#602
0$
#603
1$
b10110100 '
b10111000 (
b10110100 )
#604
0$
#605
1$
b10111000 '
b10111100 (
b10111000 )
#606
0$
#607
1$
b10111100 '
b11000000 (
b10111100 )
#608
0$
#609
1$
b11000000 '
b11000100 (
b11000000 )
#610
0$
#611
1$
b11000100 '
b11001000 (
b11000100 )
#612
0$
#613
1$
b11001000 '
b11001100 (
b11001000 )
#614
0$
#615
1$
b11001100 '
b11010000 (
b11001100 )
#616
0$
#617
1$
b11010000 '
b11010100 (
b11010000 )
#618
0$
#619
1$
b11010100 '
b11011000 (
b11010100 )
#620
0$
#621
1$
b11011000 '
b11011100 (
b11011000 )
#622
0$
#623
1$
b11011100 '
b11100000 (
b11011100 )
#624
0$
#625
1$
b11100000 '
b11100100 (
b11100000 )
#626
0$
#627
1$
b11100100 '
b11101000 (
b11100100 )
#628
0$
#629
1$
b11101000 '
b11101100 (
b11101000 )
#630
0$
#631
1$
b11101100 '
b11110000 (
b11101100 )
#632
0$
#633
1$
b11110000 '
b11110100 (
b11110000 )
#634
0$
#635
1$
b11110100 '
b11111000 (
b11110100 )
#636
0$
#637
1$
b11111000 '
b11111100 (
b11111000 )
#638
0$
#639
1$
b11111100 '
b00000000 (
b11111100 )
#640
0$
#641
1$
b00000000 '
b00000100 (
b00000000 )
#642
0$
#643
1$
b00000100 '
b00001000 (
b00000100 )
#644
0$
#645
1$
b00001000 '
b00001100 (
b00001000 )
#646
0$
#647
1$
b00001100 '
b00010000 (
b00001100 )
#648
0$
#649
1$
b00010000 '
b00010100 (
b00010000 )
#650
0$
#651
1$
b00010100 '
b00011000 (
b00010100 )
#652
0$
#653
1$
b00011000 '
b00011100 (
b00011000 )
#654
0$
#655
1$
b00011100 '
b00100000 (
b00011100 )
#656
0$
#657
1$
b00100000 '
b00100100 (
b00100000 )
#658
0$
#659
1$
b00100100 '
b00101000 (
b00100100 )
#660
0$
#661
1$
b00101000 '
b00101100 (
b00101000 )
#662
0$
#663
1$
b00101100 '
b00110000 (
b00101100 )
#664
0$
#665
1$
b00110000 '
b00110100 (
b00110000 )
#666
0$
#667
1$
b00110100 '
b00111000 (
b00110100 )
#668
0$
#669
1$
b00111000 '
b00111100 (
b00111000 )
#670
0$
#671
1$
b00111100 '
b01000000 (
b00111100 )
#672
0$
#673
1$
b01000000 '
b01000100 (
b01000000 )
#674
0$
#675
1$
b01000100 '
b01001000 (
b01000100 )
#676
0$
#677
1$
b01001000 '
b01001100 (
b01001000 )
#678
0$
#679
1$
b01001100 '
b01010000 (
b01001100 )
#680
0$
#681
1$
b01010000 '
b01010100 (
b01010000 )
#682
0$
#683
1$
b01010100 '
b01011000 (
b01010100 )
#684
0$
#685
1$
b01011000 '
b01011100 (
b01011000 )
#686
0$
#687
1$
b01011100 '
b01100000 (
b01011100 )
#688
0$
#689
1$
b01100000 '
b01100100 (
b01100000 )
#690
0$
#691
1$
b01100100 '
b01101000 (
b01100100 )
#692
0$
#693
1$
b01101000 '
b01101100 (
b01101000 )
#694
0$
#695
1$
b01101100 '
b01110000 (
b01101100 )
#696
0$
#697
1$
b01110000 '
b01110100 (
b01110000 )
#698
0$
#699
1$
b01110100 '
b01111000 (
b01110100 )
#700
0$
#701
1$
b01111000 '
b01111100 (
b01111000 )
#702
0$
#703
1$
b01111100 '
b10000000 (
b01111100 )
#704
0$
#705
1$
b10000000 '
b10000100 (
b10000000 )
#706
0$
#707
1$
b10000100 '
b10001000 (
b10000100 )
#708
0$
#709
1$
b10001000 '
b10001100 (
b10001000 )
#710
0$
#711
1$
b10001100 '
b10010000 (
b10001100 )
#712
0$
#713
1$
b10010000 '
b10010100 (
b10010000 )
#714
0$
#715
1$
b10010100 '
b10011000 (
b10010100 )
#716
0$
#717
1$
b10011000 '
b10011100 (
b10011000 )
#718
0$
#719
1$
b10011100 '
b10100000 (
b10011100 )
#720
0$
#721
1$
b10100000 '
b10100100 (
b10100000 )
#722
0$
#723
1$
b10100100 '
b10101000 (
b10100100 )
#724
0$
#725
1$
b10101000 '
b10101100 (
b10101000 )
#726
0$
#727
1$
b10101100 '
b10110000 (
b10101100 )
#728
0$
#729
1$
b10110000 '
b10110100 (
b10110000 )
#730
0$
#731
1$
b10110100 '
b10111000 (
b10110100 )
#732
0$
#733
1$
b10111000 '
b10111100 (
b10111000 )
#734
0$
#735
1$
b10111100 '
b11000000 (
b10111100 )
#736
0$
#737
1$
b11000000 '
b11000100 (
b11000000 )
#738
0$
#739
1$
b11000100 '
b11001000 (
b11000100 )
#740
0$
#741
1$
b11001000 '
b11001100 (
b11001000 )
#742
0$
#743
1$
b11001100 '
b11010000 (
b11001100 )
#744
0$
#745
1$
b11010000 '
b11010100 (
b11010000 )
#746
0$
#747
1$
b11010100 '
b11011000 (
b11010100 )
#748
0$
#749
1$
b11011000 '
b11011100 (
b11011000 )
#750
0$
#751
1$
b11011100 '
b11100000 (
b11011100 )
#752
0$
#753
1$
b11100000 '
b11100100 (
b11100000 )
#754
0$
#755
1$
b11100100 '
b11101000 (
b11100100 )
#756
0$
#757
1$
b11101000 '
b11101100 (
b11101000 )
#758
0$
#759
1$
b11101100 '
b11110000 (
b11101100 )
#760
0$
#761
1$
b11110000 '
b11110100 (
b11110000 )
#762
0$
#763
1$
b11110100 '
b11111000 (
b11110100 )
#764
0$
#765
1$
b11111000 '
b11111100 (
b11111000 )
#766
0$
#767
1$
b11111100 '
b00000000 (
b11111100 )
#768
0$
#769
1$
b00000000 '
b00000100 (
b00000000 )
#770
0$
#771
1$
b00000100 '
b00001000 (
b00000100 )
#772
0$
#773
1$
b00001000 '
b00001100 (
b00001000 )
#774
0$
#775
1$
b00001100 '
b00010000 (
b00001100 )
#776
0$
#777
1$
b00010000 '
b00010100 (
b00010000 )
#778
0$
#779
1$
b00010100 '
b00011000 (
b00010100 )
#780
0$
#781
1$
b00011000 '
b00011100 (
b00011000 )
#782
0$
#783
1$
b00011100 '
b00100000 (
b00011100 )
#784
0$
#785
1$
b00100000 '
b00100100 (
b00100000 )
#786
0$
#787
1$
b00100100 '
b00101000 (
b00100100 )
#788
0$
#789
1$
b00101000 '
b00101100 (
b00101000 )
#790
0$
#791
1$
b00101100 '
b00110000 (
b00101100 )
#792
0$
#793
1$
b00110000 '
b00110100 (
b00110000 )
#794
0$
#795
1$
b00110100 '
b00111000 (
b00110100 )
#796
0$
#797
1$
b00111000 '
b00111100 (
b00111000 )
#798
0$
#799
1$
b00111100 '
b01000000 (
b00111100 )
#800
0$
#801
1$
b01000000 '
b01000100 (
b01000000 )
#802
0$
#803
1$
b01000100 '
b01001000 (
b01000100 )
#804
0$
#805
1$
b01001000 '
b01001100 (
b01001000 )
#806
0$
#807
1$
b01001100 '
b01010000 (
b01001100 )
#808
0$
#809
1$
b01010000 '
b01010100 (
b01010000 )
#810
0$
#811
1$
b01010100 '
b01011000 (
b01010100 )
#812
0$
#813
1$
b01011000 '
b01011100 (
b01011000 )
#814
0$
#815
1$
b01011100 '
b01100000 (
b01011100 )
#816
0$
#817
1$
b01100000 '
b01100100 (
b01100000 )
#818
0$
#819
1$
b01100100 '
b01101000 (
b01100100 )
#820
0$
#821
1$
b01101000 '
b01101100 (
b01101000 )
#822
0$
#823
1$
b01101100 '
b01110000 (
b01101100 )
#824
0$
#825
1$
b01110000 '
b01110100 (
b01110000 )
#826
0$
#827
1$
b01110100 '
b01111000 (
b01110100 )
#828
0$
#829
1$
b01111000 '
b01111100 (
b01111000 )
#830
0$
#831
1$
b01111100 '
b10000000 (
b01111100 )
#832
0$
#833
1$
b10000000 '
b10000100 (
b10000000 )
#834
0$
#835
1$
b10000100 '
b10001000 (
b10000100 )
#836
0$
#837
1$
b10001000 '
b10001100 (
b10001000 )
#838
0$
#839
1$
b10001100 '
b10010000 (
b10001100 )
#840
0$
#841
1$
b10010000 '
b10010100 (
b10010000 )
#842
0$
#843
1$
b10010100 '
b10011000 (
b10010100 )
#844
0$
#845
1$
b10011000 '
b10011100 (
b10011000 )
#846
0$
#847
1$
b10011100 '
b10100000 (
b10011100 )
#848
0$
